blog/__init__.py
blog/admin.py
blog/apps.py
blog/managers.py
blog/models.py
blog/permissions.py
blog/serializers.py
blog/signals.py
blog/tasks.py
blog/urls.py
blog/views.py
blog/migrations/0001_initial.py
blog/migrations/0002_entry_title.py
blog/migrations/0003_auto_20200302_0056.py
blog/migrations/0004_auto_20200302_0126.py
blog/migrations/0005_profile.py
blog/migrations/0006_comment.py
blog/migrations/0007_entry_entry_id.py
blog/migrations/0008_profile_gravatar_url.py
blog/migrations/0009_auto_20200309_1619.py
blog/migrations/0010_auto_20200309_1619.py
blog/migrations/0011_entryenvelope_slug.py
blog/migrations/0012_auto_20200604_0048.py
blog/migrations/0013_entryenvelope_version.py
blog/migrations/0014_auto_20200609_0947.py
blog/migrations/0015_entryenvelope_defunct.py
blog/migrations/0016_profile_token.py
blog/migrations/0017_profile_url.py
blog/migrations/0018_auto_20201009_2216.py
blog/migrations/0019_auto_20201010_0842.py
blog/migrations/0020_auto_20210119_1042.py
blog/migrations/0021_view_session_uid.py
blog/migrations/0022_view_entry_id.py
blog/migrations/0023_auto_20210122_1725.py
blog/migrations/0024_visitorprofile.py
blog/migrations/0025_auto_20210124_1919.py
blog/migrations/0026_auto_20210124_2049.py
blog/migrations/0027_visitorprofile_language.py
blog/migrations/0028_auto_20210126_2304.py
blog/migrations/0029_auto_20210126_2305.py
blog/migrations/0030_interaction_session_uid.py
blog/migrations/0031_comment_approved.py
blog/migrations/0032_auto_20210625_1353.py
blog/migrations/0033_alter_entryenvelope_future_publish_date_and_more.py
blog/migrations/__init__.py
django_tcb_blog-0.11.6.dist-info/licenses/LICENSE
django_tcb_blog-0.11.6.dist-info/METADATA
django_tcb_blog-0.11.6.dist-info/WHEEL
django_tcb_blog-0.11.6.dist-info/top_level.txt
django_tcb_blog-0.11.6.dist-info/RECORD
